qrngotp/__init__.py
qrngotp/functions.py
qrngotp/greet.py
QRNG_QL_OT-0.0.1.dist-info/LICENSE
QRNG_QL_OT-0.0.1.dist-info/METADATA
QRNG_QL_OT-0.0.1.dist-info/WHEEL
QRNG_QL_OT-0.0.1.dist-info/top_level.txt
QRNG_QL_OT-0.0.1.dist-info/RECORD
