Metadata-Version: 2.1
Name: QRNG-QL-OT
Version: 0.0.1
Summary: Quantam QRNG for OTP
Home-page: https://github.com/zuburz/quantlase_OTP
Author: auth
Author-email: Hammad <hammadzahid2254@gmail.com>
License: MIT
Project-URL: url, https://github.com/zuburz/quantlase_OTP
Project-URL: Bug Tracker, https://github.com/zuburz/quantlase_OTP/issues
Classifier: Programming Language :: Python :: 3
Classifier: License :: OSI Approved :: MIT License
Classifier: Operating System :: OS Independent
Requires-Python: >=3.7
License-File: LICENSE
